bayesian_bootstrap/__init__.py
bayesian_bootstrap-1.1.0.dist-info/LICENSE
bayesian_bootstrap-1.1.0.dist-info/METADATA
bayesian_bootstrap-1.1.0.dist-info/WHEEL
bayesian_bootstrap-1.1.0.dist-info/top_level.txt
bayesian_bootstrap-1.1.0.dist-info/RECORD
